block_wrangler/__init__.py
block_wrangler/_rich_log.py
block_wrangler/block_collections.py
block_wrangler/block_type.py
block_wrangler/config.py
block_wrangler/filters.py
block_wrangler/flags.py
block_wrangler/irange.py
block_wrangler/mapping.py
block_wrangler/progress_sync.py
block_wrangler/tag.py
block_wrangler/library/__init__.py
block_wrangler/library/factories.py
block_wrangler/library/blocks/__init__.py
block_wrangler/library/blocks/minecraft.py
block_wrangler/library/tags/__init__.py
block_wrangler/library/tags/lights.py
block_wrangler/library/tags/plants.py
block_wrangler/library/tags/sway.py
block_wrangler/library/tags/waterlogged.py
block_wrangler/library/tags/generated/__init__.py
block_wrangler/library/tags/generated/minecraft/__init__.py
block_wrangler/library/tags/generated/minecraft/acacia_logs.py
block_wrangler/library/tags/generated/minecraft/all_hanging_signs.py
block_wrangler/library/tags/generated/minecraft/all_signs.py
block_wrangler/library/tags/generated/minecraft/ancient_city_replaceable.py
block_wrangler/library/tags/generated/minecraft/animals_spawnable_on.py
block_wrangler/library/tags/generated/minecraft/anvil.py
block_wrangler/library/tags/generated/minecraft/armadillo_spawnable_on.py
block_wrangler/library/tags/generated/minecraft/axolotls_spawnable_on.py
block_wrangler/library/tags/generated/minecraft/azalea_grows_on.py
block_wrangler/library/tags/generated/minecraft/azalea_root_replaceable.py
block_wrangler/library/tags/generated/minecraft/badlands_terracotta.py
block_wrangler/library/tags/generated/minecraft/bamboo_blocks.py
block_wrangler/library/tags/generated/minecraft/bamboo_plantable_on.py
block_wrangler/library/tags/generated/minecraft/banners.py
block_wrangler/library/tags/generated/minecraft/base_stone_nether.py
block_wrangler/library/tags/generated/minecraft/base_stone_overworld.py
block_wrangler/library/tags/generated/minecraft/bats_spawnable_on.py
block_wrangler/library/tags/generated/minecraft/beacon_base_blocks.py
block_wrangler-0.0.7.dist-info/LICENSE
block_wrangler-0.0.7.dist-info/METADATA
block_wrangler-0.0.7.dist-info/WHEEL
block_wrangler-0.0.7.dist-info/top_level.txt
block_wrangler-0.0.7.dist-info/RECORD
