Metadata-Version: 2.1
Name: block_wrangler
Version: 0.0.7
Summary: Use block features instead of block IDs! (for Minecraft shaderpacks)
Project-URL: Homepage, https://github.com/camplowell/block_wrangler
Project-URL: Issues, https://github.com/camplowell/block_wrangler/issues
License-File: LICENSE
Requires-Dist: rich==13.7.1
Requires-Dist: case-converter==1.1.0
Provides-Extra: fuzzy-tags
Requires-Dist: rapidfuzz; extra == "fuzzy-tags"
Provides-Extra: dev
Requires-Dist: block_wrangler[fuzzy_tags]; extra == "dev"
Requires-Dist: Jinja2==3.1.4; extra == "dev"
Requires-Dist: setuptools; extra == "dev"
Requires-Dist: twine; extra == "dev"
Requires-Dist: build; extra == "dev"
